[{"id": "4eac8174-8f96-4a22-9e3d-ef3e9096cf40", "Date": "2017-06-01", "Total Signatories": "51", "Publishing open data using IATI": "37", "Publishing data on their humanitarian activities": "31", "Using v2.02 of the IATI standard or later": "16", "Providing more granular v2.02": "0", "Providing more granular v2.03": "NOT MEASURED", "Publishing Traceability Information": "NOT MEASURED"}, {"id": "4516a76e-79b9-44b1-bd2a-0dffc751e804", "Date": "2018-05-01", "Total Signatories": "59", "Publishing open data using IATI": "44", "Publishing data on their humanitarian activities": "36", "Using v2.02 of the IATI standard or later": "31", "Providing more granular v2.02": "8", "Providing more granular v2.03": "NOT MEASURED", "Publishing Traceability Information": "NOT MEASURED"}, {"id": "95c73fda-fd22-4791-9fb6-82f64eb8e753", "Date": "2019-05-01", "Total Signatories": "59", "Publishing open data using IATI": "48", "Publishing data on their humanitarian activities": "43", "Using v2.02 of the IATI standard or later": "41", "Providing more granular v2.02": "14", "Providing more granular v2.03": "NOT MEASURED", "Publishing Traceability Information": "NOT MEASURED"}, {"id": "618eeecf-d626-4d52-9ee4-b810a17f220d", "Date": "2020-01-06", "Total Signatories": "61", "Publishing open data using IATI": "52", "Publishing data on their humanitarian activities": "48", "Using v2.02 of the IATI standard or later": "46", "Providing more granular v2.02": "14", "Providing more granular v2.03": "4", "Publishing Traceability Information": "17"}, {"id": "", "Date": "2021-07-20", "Total Signatories": 63, "Publishing open data using IATI": 52, "Publishing data on their humanitarian activities": 52, "Using v2.02 of the IATI standard or later": 53, "Providing more granular v2.02": 41, "Providing more granular v2.03": 9, "Publishing Traceability Information": 29}]